[
  {
    "url": "https://bbs.byr.cn/article/Friends/1862590",
    "title": "[王道]替本科巨优秀又美腻的师姐征个友~",
    "count": 80
  },
  {
    "url": "https://bbs.byr.cn/article/Feeling/3051550",
    "title": "有一个姑娘",
    "count": 73
  },
  {
    "url": "https://bbs.byr.cn/article/Talking/5995002",
    "title": "清明想去西安玩，交通工具以及景点",
    "count": 56
  },
  {
    "url": "https://bbs.byr.cn/article/Picture/3210091",
    "title": "在食堂里连续吃出虫子",
    "count": 37
  },
  {
    "url": "https://bbs.byr.cn/article/WorkLife/1100535",
    "title": "【心得】关于毕业，留京与前途，说说实力、运气与成功",
    "count": 26
  },
  {
    "url": "https://bbs.byr.cn/article/StudyShare/183143",
    "title": "想保研北大 求指点",
    "count": 19
  },
  {
    "url": "https://bbs.byr.cn/article/AimGraduate/1140130",
    "title": "[经验贴]信通考研经验分享",
    "count": 17
  },
  {
    "url": "https://bbs.byr.cn/article/Beauty/322572",
    "title": "【求同伴】清明节本周去医院看痘痘？",
    "count": 17
  },
  {
    "url": "https://bbs.byr.cn/article/Shandong/417222",
    "title": "趣事",
    "count": 16
  },
  {
    "url": "https://bbs.byr.cn/article/MobileTerminalAT/33898",
    "title": "佳邮支持iPhoneX",
    "count": 15
  }
]