[
  {
    "url": "https://bbs.byr.cn/article/Talking/6100933",
    "title": "【求起名】刘姓男宝宝求起名",
    "count": 95
  },
  {
    "url": "https://bbs.byr.cn/article/Feeling/3102190",
    "title": "女生身高太高男生会介意吗",
    "count": 65
  },
  {
    "url": "https://bbs.byr.cn/article/Picture/3237861",
    "title": "洗漱间惨案",
    "count": 45
  },
  {
    "url": "https://bbs.byr.cn/article/Java/61314",
    "title": "做了一个web版多人实时对战的坦克小游戏",
    "count": 37
  },
  {
    "url": "https://bbs.byr.cn/article/Job/2018736",
    "title": "实习疑惑 腾讯",
    "count": 19
  },
  {
    "url": "https://bbs.byr.cn/article/Friends/1913531",
    "title": "帮朋友征男友ps:漂亮小姐姐",
    "count": 18
  },
  {
    "url": "https://bbs.byr.cn/article/Notebook/178505",
    "title": "求问大神ipad摔成这样还能修好不？",
    "count": 17
  },
  {
    "url": "https://bbs.byr.cn/article/AimGraduate/1158665",
    "title": "【问题】2019年北邮推荐免试研究生名单",
    "count": 14
  },
  {
    "url": "https://bbs.byr.cn/article/AutoMotor/126473",
    "title": "昂克赛拉还是雷凌双擎？",
    "count": 13
  },
  {
    "url": "https://bbs.byr.cn/article/ACM_ICPC/97655",
    "title": "时间复杂性用大O还是大theta更合适？为什么？",
    "count": 11
  }
]