[
  {
    "url": "https://bbs.byr.cn/article/WorkLife/1115999",
    "title": "【户口】大家都打算在北京定居吗？如果买不起房户口有什么意义",
    "count": 94
  },
  {
    "url": "https://bbs.byr.cn/article/Feeling/3098832",
    "title": "想谈一下我对另一半的希望",
    "count": 74
  },
  {
    "url": "https://bbs.byr.cn/article/DigiLife/306674",
    "title": "父母用的千元机求推荐",
    "count": 71
  },
  {
    "url": "https://bbs.byr.cn/article/Talking/6091297",
    "title": "信通大二求问",
    "count": 36
  },
  {
    "url": "https://bbs.byr.cn/article/BUPTNet/99592",
    "title": "校园网看微博视频的问题",
    "count": 32
  },
  {
    "url": "https://bbs.byr.cn/article/Picture/3234771",
    "title": "狗命要紧",
    "count": 30
  },
  {
    "url": "https://bbs.byr.cn/article/Security/43898",
    "title": "【2019】腾讯科恩实验室招聘web安全实习生，欢迎学弟学妹们投递",
    "count": 20
  },
  {
    "url": "https://bbs.byr.cn/article/Friends/1908958",
    "title": "坐标北京，认真寻找心动女孩",
    "count": 20
  },
  {
    "url": "https://bbs.byr.cn/article/Job/2014920",
    "title": "【求助】我能干嘛？",
    "count": 12
  },
  {
    "url": "https://bbs.byr.cn/article/Paper/32445",
    "title": "wcnc现在edas bug可查了么",
    "count": 12
  }
]