[
  {
    "url": "https://bbs.byr.cn/article/CivilServant/43822",
    "title": "21届有想去体制内的吗？",
    "count": 87
  },
  {
    "url": "https://bbs.byr.cn/article/Job/2088584",
    "title": "保研or工作 \u0026amp;  微软/阿里云  offer 选择",
    "count": 50
  },
  {
    "url": "https://bbs.byr.cn/article/Picture/3257065",
    "title": "自己画的新表情包",
    "count": 46
  },
  {
    "url": "https://bbs.byr.cn/article/Talking/6195878",
    "title": "有申请返京成功的吗",
    "count": 37
  },
  {
    "url": "https://bbs.byr.cn/article/Notebook/181600",
    "title": "求推荐轻薄游戏本",
    "count": 23
  },
  {
    "url": "https://bbs.byr.cn/article/WorkLife/1145001",
    "title": "【暑期实习比较】招行卡中心vs大摩",
    "count": 19
  },
  {
    "url": "https://bbs.byr.cn/article/Feeling/3145729",
    "title": "今天是情人节，想和前任发个消息，发个什么好呢",
    "count": 19
  },
  {
    "url": "https://bbs.byr.cn/article/AimGraduate/1188473",
    "title": "有了解南方科技大学的吗？",
    "count": 19
  },
  {
    "url": "https://bbs.byr.cn/article/Constellations/326533",
    "title": "【转】超神准！星座小王子独创的新型占卜、來一起試玩一下！",
    "count": 17
  },
  {
    "url": "https://bbs.byr.cn/article/Paper/40476",
    "title": "attention是怎么把注意力集中在关键位置的",
    "count": 7
  }
]