[
  {
    "url": "https://bbs.byr.cn/article/Friends/1964813",
    "title": "【代征友】95年女生~坐标上海",
    "count": 73
  },
  {
    "url": "https://bbs.byr.cn/article/AimGraduate/1192868",
    "title": "【公告】网络技术研究院网络管理研究中心（2组）2021招生",
    "count": 35
  },
  {
    "url": "https://bbs.byr.cn/article/Talking/6207297",
    "title": "张含韵她不香吗？",
    "count": 34
  },
  {
    "url": "https://bbs.byr.cn/article/Paper/41300",
    "title": "老师今天说学校规定必须发列表的会才能毕业",
    "count": 23
  },
  {
    "url": "https://bbs.byr.cn/article/Job/2094451",
    "title": "嘉实基金远见科技和360 算法实习比较",
    "count": 19
  },
  {
    "url": "https://bbs.byr.cn/article/Feeling/3150218",
    "title": "十年，你可安好",
    "count": 16
  },
  {
    "url": "https://bbs.byr.cn/article/Constellations/326533",
    "title": "【转】超神准！星座小王子独创的新型占卜、來一起試玩一下！",
    "count": 14
  },
  {
    "url": "https://bbs.byr.cn/article/DigiLife/314466",
    "title": "2020返校季送耳机",
    "count": 14
  },
  {
    "url": "https://bbs.byr.cn/article/BoardGame/56265",
    "title": "狼人杀求组织！",
    "count": 11
  },
  {
    "url": "https://bbs.byr.cn/article/WorkLife/1148340",
    "title": "事业单位和国企都默认不喜欢要已婚女生吗？",
    "count": 10
  }
]