[
  {
    "title": "专硕电子信息专业已有多所学校着手改名",
    "url": "https://bbs.byr.cn/article/Talking/6313617",
    "count": 32
  },
  {
    "title": "坐标合肥，想换个工作，求交流",
    "url": "https://bbs.byr.cn/article/WorkLife/1179727",
    "count": 24
  },
  {
    "title": "论眯眯眼",
    "url": "https://bbs.byr.cn/article/Picture/3309939",
    "count": 23
  },
  {
    "title": "博士offer（杭州）求比较",
    "url": "https://bbs.byr.cn/article/Job/2153851",
    "count": 19
  },
  {
    "title": "找小伙伴一起去滑雪",
    "url": "https://bbs.byr.cn/article/Ski_Snowboard/1052",
    "count": 16
  },
  {
    "title": "泸溪河可以小程序点餐再自提吗",
    "url": "https://bbs.byr.cn/article/Food/517776",
    "count": 13
  },
  {
    "title": "导师给的方向一头雾水，求指导",
    "url": "https://bbs.byr.cn/article/ML_DM/38121",
    "count": 12
  },
  {
    "title": "呼吁学校出台留校政策时对陕西籍学生有相关措施",
    "url": "https://bbs.byr.cn/article/Shaanxi/121905",
    "count": 10
  },
  {
    "title": "捞人后续",
    "url": "https://bbs.byr.cn/article/Feeling/3182799",
    "count": 9
  },
  {
    "title": "笔记本选择：惠普暗影精灵7 vs 戴尔G15",
    "url": "https://bbs.byr.cn/article/Notebook/182855",
    "count": 9
  }
]