[
  {
    "url": "https://bbs.byr.cn/article/Music/342392",
    "title": "各位有什么自带画面感的歌吗",
    "count": 53
  },
  {
    "url": "https://bbs.byr.cn/article/Talking/6256527",
    "title": "求花名~",
    "count": 42
  },
  {
    "url": "https://bbs.byr.cn/article/WorkLife/1161543",
    "title": "【讨论】闷头做技术有前途吗？",
    "count": 40
  },
  {
    "url": "https://bbs.byr.cn/article/Friends/1984931",
    "title": "[代征]代95年小姐姐征友",
    "count": 19
  },
  {
    "url": "https://bbs.byr.cn/article/Jiangxi/468949",
    "title": "【问题】今年有多少老表留京过年了？",
    "count": 19
  },
  {
    "url": "https://bbs.byr.cn/article/Feeling/3163574",
    "title": "什么时候可以摆脱这个状态",
    "count": 12
  },
  {
    "url": "https://bbs.byr.cn/article/Job/2124390",
    "title": "【春招户口offer】求指点",
    "count": 12
  },
  {
    "url": "https://bbs.byr.cn/article/Hebei/249698",
    "title": "保定学长学姐有去长城的吗",
    "count": 8
  },
  {
    "url": "https://bbs.byr.cn/article/Constellations/326533",
    "title": "【转】超神准！星座小王子独创的新型占卜、來一起試玩一下！",
    "count": 7
  },
  {
    "url": "https://bbs.byr.cn/article/Selfsupport/23415",
    "title": "1月研究生补助还没发呢？",
    "count": 6
  }
]