[
  {
    "title": "[代发]【王道】北京90年女生真诚征友",
    "url": "https://bbs.byr.cn/article/Friends/2031613",
    "count": 32
  },
  {
    "title": "接海尔还是卷银行，请各位积极发言",
    "url": "https://bbs.byr.cn/article/Shandong/422947",
    "count": 21
  },
  {
    "title": "沙雕图10.22",
    "url": "https://bbs.byr.cn/article/Picture/3331399",
    "count": 15
  },
  {
    "title": "【转】超神准！星座小王子独创的新型占卜、來一起試玩一下！",
    "url": "https://bbs.byr.cn/article/Constellations/326533",
    "count": 13
  },
  {
    "title": "请问有人了解“杭州兵智科技”嘛？",
    "url": "https://bbs.byr.cn/article/Job/2173365",
    "count": 12
  },
  {
    "title": "请赐予我offer吧！",
    "url": "https://bbs.byr.cn/article/GoAbroad/368912",
    "count": 10
  },
  {
    "title": "有Linux系统安好的Gnu radio吗，实在安不上",
    "url": "https://bbs.byr.cn/article/Linux/160798",
    "count": 10
  },
  {
    "title": "毕业一年从0学日语为了去日工作",
    "url": "https://bbs.byr.cn/article/Talking/6368418",
    "count": 10
  },
  {
    "title": "【我不允许和我遇到同样问题的人还不知道！】休眠重启后连不上",
    "url": "https://bbs.byr.cn/article/Windows/126933",
    "count": 7
  },
  {
    "title": "这是哪位学弟……五星图有点吓人啊",
    "url": "https://bbs.byr.cn/article/Dota/959389",
    "count": 6
  }
]