[
  {
    "title": "为啥美国入侵那么多国家没人骂，俄罗斯打乌克兰大家都炸了",
    "url": "https://bbs.byr.cn/article/Picture/3313591",
    "count": 47
  },
  {
    "title": "关于疫情的提问",
    "url": "https://bbs.byr.cn/article/Talking/6332416",
    "count": 42
  },
  {
    "title": "男孩和女孩",
    "url": "https://bbs.byr.cn/article/Feeling/3185608",
    "count": 36
  },
  {
    "title": "冲蛋白粉的杯子好臭，怎么办",
    "url": "https://bbs.byr.cn/article/Gymnasium/119463",
    "count": 32
  },
  {
    "title": "至今无offer，很难受",
    "url": "https://bbs.byr.cn/article/GoAbroad/383647",
    "count": 27
  },
  {
    "title": "【代征】 00年 水瓶座 武汉 女生征友",
    "url": "https://bbs.byr.cn/article/Friends/2018112",
    "count": 24
  },
  {
    "title": "【转】超神准！星座小王子独创的新型占卜、來一起試玩一下！",
    "url": "https://bbs.byr.cn/article/Constellations/326533",
    "count": 24
  },
  {
    "title": "回龙观的房价涨这么狠，现在的毕业生好难",
    "url": "https://bbs.byr.cn/article/WorkLife/1182611",
    "count": 15
  },
  {
    "title": "有3月份去天津公考的byr吗",
    "url": "https://bbs.byr.cn/article/CivilServant/48682",
    "count": 8
  },
  {
    "title": "求助，运营商 or 。。。",
    "url": "https://bbs.byr.cn/article/Job/2158639",
    "count": 7
  }
]