[
  {
    "title": "女孩取名，今天出生的，采纳发百元红包",
    "url": "https://bbs.byr.cn/article/Feeling/3195280",
    "count": 62
  },
  {
    "title": "求推荐牛奶",
    "url": "https://bbs.byr.cn/article/Talking/6369804",
    "count": 42
  },
  {
    "title": "【NLPer Offer 比较】小冰\u0026amp;百度\u0026amp;阿里\u0026amp;快手\u0026amp;商汤",
    "url": "https://bbs.byr.cn/article/Job/2175485",
    "count": 38
  },
  {
    "title": "[坐标深圳]替人美声柔的好朋友征人生另一半",
    "url": "https://bbs.byr.cn/article/Friends/2032748",
    "count": 34
  },
  {
    "title": "【转】超神准！星座小王子独创的新型占卜、來一起試玩一下！",
    "url": "https://bbs.byr.cn/article/Constellations/326533",
    "count": 22
  },
  {
    "title": "沙雕图11.09",
    "url": "https://bbs.byr.cn/article/Picture/3332575",
    "count": 16
  },
  {
    "title": "皮肤科医生求推荐",
    "url": "https://bbs.byr.cn/article/Health/229930",
    "count": 14
  },
  {
    "title": "【讨论】【问题】河南人留在北京",
    "url": "https://bbs.byr.cn/article/Henan/390805",
    "count": 11
  },
  {
    "title": "「ギターと孤独と蒼い惑星」太有感觉了……",
    "url": "https://bbs.byr.cn/article/Comic/632557",
    "count": 10
  },
  {
    "title": "外企裁员会不会从中国开始啊",
    "url": "https://bbs.byr.cn/article/WorkLife/1188981",
    "count": 8
  }
]