[
  {
    "title": "悬赏500元！！（主楼的进）有偿悬赏被偷iwatch",
    "url": "https://bbs.byr.cn/article/Talking/6404777",
    "count": 125
  },
  {
    "title": "大厂必修课",
    "url": "https://bbs.byr.cn/article/WorkLife/1206474",
    "count": 24
  },
  {
    "title": "【王道】代八八年女同学征男友",
    "url": "https://bbs.byr.cn/article/Friends/2047171",
    "count": 19
  },
  {
    "title": "名人堂＋1，树哥",
    "url": "https://bbs.byr.cn/article/Picture/3353353",
    "count": 18
  },
  {
    "title": "[校招offer求助]",
    "url": "https://bbs.byr.cn/article/Job/2198911",
    "count": 17
  },
  {
    "title": "【转】超神准！星座小王子独创的新型占卜、來一起試玩一下！",
    "url": "https://bbs.byr.cn/article/Constellations/326533",
    "count": 11
  },
  {
    "title": "求问：游泳馆什么时候开",
    "url": "https://bbs.byr.cn/article/Swim/130279",
    "count": 11
  },
  {
    "title": "新建了个byr投资交流群，欢迎各位进来讨论吹水",
    "url": "https://bbs.byr.cn/article/Financial/80130",
    "count": 10
  },
  {
    "title": "校内瑞幸为什么是自己在门口打包",
    "url": "https://bbs.byr.cn/article/Food/525192",
    "count": 7
  },
  {
    "title": "[博士招生]电子工程学院刘元安团队刘凯明老师课题组招收博士生",
    "url": "https://bbs.byr.cn/article/AimGraduate/1227502",
    "count": 7
  }
]