[
  {
    "url": "https://bbs.byr.cn/article/Feeling/3130180",
    "title": "【澄清】生活远比电视剧狗血",
    "count": 267
  },
  {
    "url": "https://bbs.byr.cn/article/Talking/6167627",
    "title": "有人关注香港问题吗",
    "count": 87
  },
  {
    "url": "https://bbs.byr.cn/article/Job/2066984",
    "title": "求大家给苦难的我个建议或者出路",
    "count": 67
  },
  {
    "url": "https://bbs.byr.cn/article/Financial/76744",
    "title": "理财基金股票讨论群 带小白入场有干货",
    "count": 36
  },
  {
    "url": "https://bbs.byr.cn/article/StudyShare/193767",
    "title": "诗词接龙",
    "count": 36
  },
  {
    "url": "https://bbs.byr.cn/article/Picture/3250012",
    "title": "【问题】中国移动套餐这么贵了？？",
    "count": 32
  },
  {
    "url": "https://bbs.byr.cn/article/WorkLife/1133875",
    "title": "【转载】网易裁员，让保安把身患绝症的我赶出公司。我在网易亲",
    "count": 29
  },
  {
    "url": "https://bbs.byr.cn/article/AimGraduate/1177921",
    "title": "北京邮电大学院士实验室博士后招聘启事（年薪28-40万）",
    "count": 21
  },
  {
    "url": "https://bbs.byr.cn/article/Constellations/326533",
    "title": "【转】超神准！星座小王子独创的新型占卜、來一起試玩一下！",
    "count": 20
  },
  {
    "url": "https://bbs.byr.cn/article/GoAbroad/308384",
    "title": "欧洲和新加坡读研的问题，求咨询",
    "count": 18
  }
]