[
  {
    "url": "https://bbs.byr.cn/article/Talking/6283371",
    "title": "祝2021届毕业生毕业快乐~快来留下你的IP~",
    "count": 384
  },
  {
    "url": "https://bbs.byr.cn/article/Feeling/3173320",
    "title": "再见，再也不见~",
    "count": 75
  },
  {
    "url": "https://bbs.byr.cn/article/Friends/1997728",
    "title": "【代96年妹子诚心征友】",
    "count": 64
  },
  {
    "url": "https://bbs.byr.cn/article/Home/130270",
    "title": "【讨论】女生愿意和男朋友合资买房的比例高吗",
    "count": 27
  },
  {
    "url": "https://bbs.byr.cn/article/Picture/3292982",
    "title": "在学校里遇到了小刺猬",
    "count": 21
  },
  {
    "url": "https://bbs.byr.cn/article/WorkLife/1169557",
    "title": "【问题】我们到底在 “内卷” 什么",
    "count": 20
  },
  {
    "url": "https://bbs.byr.cn/article/Comic/631711",
    "title": "要毕业了，刚好最近新番也都开始完结",
    "count": 15
  },
  {
    "url": "https://bbs.byr.cn/article/GoAbroad/374211",
    "title": "【问题】我们19年之前的飞跃榜怎么都无了",
    "count": 14
  },
  {
    "url": "https://bbs.byr.cn/article/Job/2136934",
    "title": "【心得】秋招总结",
    "count": 9
  },
  {
    "url": "https://bbs.byr.cn/article/Constellations/326533",
    "title": "【转】超神准！星座小王子独创的新型占卜、來一起試玩一下！",
    "count": 8
  }
]