[
  {
    "title": "真的是北疣人了。。",
    "url": "https://bbs.byr.cn/article/Talking/6305014",
    "count": 8
  },
  {
    "title": "【建议大家积极维权】我和身边人近半年遇见的食品卫生安全问题",
    "url": "https://bbs.byr.cn/article/Food/516476",
    "count": 8
  },
  {
    "title": "FPX菜菜菜",
    "url": "https://bbs.byr.cn/article/LOL/29483",
    "count": 7
  },
  {
    "title": "举报体育馆猥琐大叔偷窥女浴室",
    "url": "https://bbs.byr.cn/article/Gymnasium/118921",
    "count": 5
  },
  {
    "title": "【比较】农行招行和老家铁路局",
    "url": "https://bbs.byr.cn/article/Job/2142793",
    "count": 3
  },
  {
    "title": "【毕设相关】毕设一般什么时候开题？可以自拟题目吗？",
    "url": "https://bbs.byr.cn/article/AimGraduate/1211977",
    "count": 3
  },
  {
    "title": "女生提分手后是不是就不会回头了",
    "url": "https://bbs.byr.cn/article/Feeling/3178897",
    "count": 3
  },
  {
    "title": "学10校园网丢包率过高",
    "url": "https://bbs.byr.cn/article/BUPTNet/106010",
    "count": 2
  },
  {
    "title": "select boyfriend from byr",
    "url": "https://bbs.byr.cn/article/Friends/2008081",
    "count": 2
  },
  {
    "title": "cv的文章投icassp",
    "url": "https://bbs.byr.cn/article/Paper/45452",
    "count": 1
  }
]