[
  {
    "url": "https://bbs.byr.cn/article/WorkLife/1161324",
    "title": "年终奖",
    "count": 31
  },
  {
    "url": "https://bbs.byr.cn/article/Talking/6256293",
    "title": "校友频繁上热搜学校不为所动",
    "count": 26
  },
  {
    "url": "https://bbs.byr.cn/article/Feeling/3163484",
    "title": "还有人醒着吗",
    "count": 17
  },
  {
    "url": "https://bbs.byr.cn/article/Job/2121685",
    "title": "【问题】不要户口，有没有给钱多不加班的国企？",
    "count": 16
  },
  {
    "url": "https://bbs.byr.cn/article/Friends/1984810",
    "title": "【征GG】请你喝咖啡呀",
    "count": 13
  },
  {
    "url": "https://bbs.byr.cn/article/Constellations/326533",
    "title": "【转】超神准！星座小王子独创的新型占卜、來一起試玩一下！",
    "count": 11
  },
  {
    "url": "https://bbs.byr.cn/article/Jiangxi/468918",
    "title": "有喜欢福尔摩斯的能来破解一下这个嘛",
    "count": 10
  },
  {
    "url": "https://bbs.byr.cn/article/StudyShare/199755",
    "title": "关于conda",
    "count": 5
  },
  {
    "url": "https://bbs.byr.cn/article/WOW/161881",
    "title": "【2021.01.15更新】真情部落-凤凰之神欢迎各位",
    "count": 5
  },
  {
    "url": "https://bbs.byr.cn/article/Chongqing/25286",
    "title": "北京哪里能吃豆花饭啊",
    "count": 5
  }
]