[
  {
    "title": "开贴 给zxl征友",
    "url": "https://bbs.byr.cn/article/Friends/2010923",
    "count": 12
  },
  {
    "title": "室友持刀比划我。导员说刀没开刃，对我造不成伤害。（原标题：",
    "url": "https://bbs.byr.cn/article/Talking/6313715",
    "count": 5
  },
  {
    "title": "给果园电管同学的考研经验分享以及一些答疑",
    "url": "https://bbs.byr.cn/article/AimGraduate/1212536",
    "count": 4
  },
  {
    "title": "关于电子信息20.21级细分专业",
    "url": "https://bbs.byr.cn/article/Picture/3306523",
    "count": 4
  },
  {
    "title": "【转】超神准！星座小王子独创的新型占卜、來一起試玩一下！",
    "url": "https://bbs.byr.cn/article/Constellations/326533",
    "count": 3
  },
  {
    "title": "CNM!的欧足联！葡萄牙意大利必有一个无缘世界杯",
    "url": "https://bbs.byr.cn/article/Football/810049585",
    "count": 3
  },
  {
    "title": "offer求比较",
    "url": "https://bbs.byr.cn/article/Job/2149635",
    "count": 2
  },
  {
    "title": "求助NUS申请MComp无G可以提交申请吗",
    "url": "https://bbs.byr.cn/article/GoAbroad/381387",
    "count": 1
  },
  {
    "title": "校医院做B超有什么注意事项吗",
    "url": "https://bbs.byr.cn/article/Health/227315",
    "count": 1
  },
  {
    "title": "移动研究院入职一年半的一点感受",
    "url": "https://bbs.byr.cn/article/WorkLife/1177537",
    "count": 1
  }
]