[
  {
    "title": "每天一个小惊喜",
    "url": "https://bbs.byr.cn/article/Talking/6345055",
    "count": 11
  },
  {
    "title": "【转】超神准！星座小王子独创的新型占卜、來一起試玩一下！",
    "url": "https://bbs.byr.cn/article/Constellations/326533",
    "count": 8
  },
  {
    "title": "沙雕图第4弹",
    "url": "https://bbs.byr.cn/article/Picture/3320215",
    "count": 6
  },
  {
    "title": "暑期实习offer比较 字节 美团",
    "url": "https://bbs.byr.cn/article/Job/2163211",
    "count": 4
  },
  {
    "title": "征友征破防",
    "url": "https://bbs.byr.cn/article/Feeling/3188003",
    "count": 2
  },
  {
    "title": "新四食堂辣子鸡的辣子究竟是否被回收制作辣椒油?",
    "url": "https://bbs.byr.cn/article/Food/519455",
    "count": 2
  },
  {
    "title": "[约骑] 9月24日妙峰山，挑战你的最好成绩",
    "url": "https://bbs.byr.cn/article/Cycling/173953",
    "count": 2
  },
  {
    "title": "互联网+比赛招人",
    "url": "https://bbs.byr.cn/article/Innovation/7854",
    "count": 1
  },
  {
    "title": "真的有人喜欢35mm视角吗",
    "url": "https://bbs.byr.cn/article/Photo/272894",
    "count": 1
  },
  {
    "title": "【实习】【科研】南方科技大学数据库课题组本科生科研实习招募",
    "url": "https://bbs.byr.cn/article/AimGraduate/1216837",
    "count": 1
  }
]