[
  {
    "title": "写了一首悼念联通学姐的诗",
    "url": "https://bbs.byr.cn/article/Poetry/36180",
    "count": 6
  },
  {
    "title": "【征友】2022夏++决定勇敢",
    "url": "https://bbs.byr.cn/article/Friends/2025902",
    "count": 4
  },
  {
    "title": "谈恋爱真的太烧钱了...",
    "url": "https://bbs.byr.cn/article/Feeling/3188863",
    "count": 4
  },
  {
    "title": "iPhone 13 Pro Max和索尼无反相机人像对比",
    "url": "https://bbs.byr.cn/article/Photo/273407",
    "count": 3
  },
  {
    "title": "小曾老师手撕北邮渣男-九年的青春喂了狗【聊天记录】",
    "url": "https://bbs.byr.cn/article/Picture/3323629",
    "count": 3
  },
  {
    "title": "大一学生求学长学姐解惑",
    "url": "https://bbs.byr.cn/article/Talking/6351640",
    "count": 2
  },
  {
    "title": "实习offer选择：快手服务端 vs 字节SRE",
    "url": "https://bbs.byr.cn/article/WorkLife/1186988",
    "count": 2
  },
  {
    "title": "考研择校",
    "url": "https://bbs.byr.cn/article/AimGraduate/1217348",
    "count": 1
  },
  {
    "title": "社会实践",
    "url": "https://bbs.byr.cn/article/Anhui/323856",
    "count": 1
  }
]