[
  {
    "title": "征友",
    "url": "https://bbs.byr.cn/article/Friends/2034402",
    "count": 97
  },
  {
    "title": "隔壁北交大恢复2019年校园状态 北邮呢？",
    "url": "https://bbs.byr.cn/article/Talking/6375993",
    "count": 27
  },
  {
    "title": "和男朋友因为一份外卖吵了一周",
    "url": "https://bbs.byr.cn/article/Feeling/3197353",
    "count": 21
  },
  {
    "title": "沙雕图12.28",
    "url": "https://bbs.byr.cn/article/Picture/3335203",
    "count": 20
  },
  {
    "title": "【offer比较】 联想 vs 招行 vs 光大总部",
    "url": "https://bbs.byr.cn/article/Job/2180743",
    "count": 16
  },
  {
    "title": "【全球寻人】97届北邮毕业生 佘跃华",
    "url": "https://bbs.byr.cn/article/RadioOnline/9978",
    "count": 14
  },
  {
    "title": "【转】超神准！星座小王子独创的新型占卜、來一起試玩一下！",
    "url": "https://bbs.byr.cn/article/Constellations/326533",
    "count": 10
  },
  {
    "title": "北邮学生去美国开会的话签证能过吗",
    "url": "https://bbs.byr.cn/article/GoAbroad/390468",
    "count": 10
  },
  {
    "title": "【2022总结】做试管的一年经历与感想，但仍在路上",
    "url": "https://bbs.byr.cn/article/WorkLife/1194084",
    "count": 6
  },
  {
    "title": "(实习)(兼职）创新实践",
    "url": "https://bbs.byr.cn/article/Innovation/7969",
    "count": 3
  }
]