[
  {
    "title": "找副业",
    "url": "https://bbs.byr.cn/article/Talking/6356928",
    "count": 37
  },
  {
    "title": "【0725更新银行信息】根据各大券商的信息化重视程度了作一个排",
    "url": "https://bbs.byr.cn/article/WorkLife/1189225",
    "count": 31
  },
  {
    "title": "【代征】【沈阳】替闺蜜征友",
    "url": "https://bbs.byr.cn/article/Friends/2023785",
    "count": 25
  },
  {
    "title": "【转】超神准！星座小王子独创的新型占卜、來一起試玩一下！",
    "url": "https://bbs.byr.cn/article/Constellations/326533",
    "count": 12
  },
  {
    "title": "【心得】【讨论】【建议】2023fall申请，个人bg+各国项目/学校/",
    "url": "https://bbs.byr.cn/article/GoAbroad/387894",
    "count": 11
  },
  {
    "title": "国企会因为报到证没到毁三方吗？",
    "url": "https://bbs.byr.cn/article/Job/2168298",
    "count": 8
  },
  {
    "title": "循 环 论 证",
    "url": "https://bbs.byr.cn/article/Picture/3325498",
    "count": 7
  },
  {
    "title": "求推荐音质好的蓝牙耳机",
    "url": "https://bbs.byr.cn/article/DigiLife/317574",
    "count": 7
  },
  {
    "title": "开帖聊聊2022年的54所（伪招人帖）",
    "url": "https://bbs.byr.cn/article/Hebei/250988",
    "count": 7
  },
  {
    "title": "有最近上车「建发珺和府」的校友吗？",
    "url": "https://bbs.byr.cn/article/Home/133202",
    "count": 3
  }
]