[
  {
    "title": "【讨论】2022过得开心吗",
    "url": "https://bbs.byr.cn/article/Feeling/3197455",
    "count": 4
  },
  {
    "title": "【offer比较】微软 vs 电信集团",
    "url": "https://bbs.byr.cn/article/Job/2180912",
    "count": 2
  },
  {
    "title": "【转】超神准！星座小王子独创的新型占卜、來一起試玩一下！",
    "url": "https://bbs.byr.cn/article/Constellations/326533",
    "count": 2
  },
  {
    "title": "沙雕图12.30",
    "url": "https://bbs.byr.cn/article/Picture/3335250",
    "count": 2
  },
  {
    "title": "补考上60分就说明补考过了吗",
    "url": "https://bbs.byr.cn/article/StudyShare/205282",
    "count": 1
  },
  {
    "title": "【2022总结】山重水复疑无路",
    "url": "https://bbs.byr.cn/article/WorkLife/1194259",
    "count": 1
  },
  {
    "title": "【代征】98年女生（有王道）",
    "url": "https://bbs.byr.cn/article/Friends/2034499",
    "count": 1
  },
  {
    "title": "有个建议不知道大家赞不赞同",
    "url": "https://bbs.byr.cn/article/Talking/6376541",
    "count": 1
  }
]