[
  {
    "title": "谈恋爱真的太烧钱了...",
    "url": "https://bbs.byr.cn/article/Feeling/3188863",
    "count": 34
  },
  {
    "title": "感觉自己没有朝气怎么办？",
    "url": "https://bbs.byr.cn/article/Talking/6350928",
    "count": 23
  },
  {
    "title": "应届生：腾讯vs北京某事业编",
    "url": "https://bbs.byr.cn/article/Job/2165867",
    "count": 16
  },
  {
    "title": "给自己征友",
    "url": "https://bbs.byr.cn/article/Friends/2025854",
    "count": 14
  },
  {
    "title": "【转】超神准！星座小王子独创的新型占卜、來一起試玩一下！",
    "url": "https://bbs.byr.cn/article/Constellations/326533",
    "count": 12
  },
  {
    "title": "爱打COC部落战的北邮人快来！",
    "url": "https://bbs.byr.cn/article/OnlineGame/43768",
    "count": 12
  },
  {
    "title": "亦庄京东合租",
    "url": "https://bbs.byr.cn/article/Home/132950",
    "count": 9
  },
  {
    "title": "offer选择：腾讯or研究院",
    "url": "https://bbs.byr.cn/article/WorkLife/1185861",
    "count": 6
  },
  {
    "title": "6月20-7月初 北疆求驴友",
    "url": "https://bbs.byr.cn/article/Xinjiang/168004",
    "count": 4
  },
  {
    "title": "多大计算机学费30万人民币，飞跃榜上同学这么好有钱",
    "url": "https://bbs.byr.cn/article/GoAbroad/386623",
    "count": 3
  }
]