[
  {
    "title": "互联网 vs 银行总行",
    "url": "https://bbs.byr.cn/article/Job/2155974",
    "count": 11
  },
  {
    "title": "原来，生活早已开始",
    "url": "https://bbs.byr.cn/article/Talking/6326125",
    "count": 8
  },
  {
    "title": "【转】超神准！星座小王子独创的新型占卜、來一起試玩一下！",
    "url": "https://bbs.byr.cn/article/Constellations/326533",
    "count": 4
  },
  {
    "title": "求问伦敦留学体验",
    "url": "https://bbs.byr.cn/article/GoAbroad/382305",
    "count": 4
  },
  {
    "title": "微软687亿美元收购动视暴雪Activision Blizzard",
    "url": "https://bbs.byr.cn/article/Hearthstone/3036",
    "count": 3
  },
  {
    "title": "【讨论】想计划自己建个新的天津byr求职定居落户聊天群...欢迎",
    "url": "https://bbs.byr.cn/article/Tianjin/67403",
    "count": 3
  },
  {
    "title": "征友信息大集合【发现和你一样特别的人】",
    "url": "https://bbs.byr.cn/article/Friends/1971258",
    "count": 1
  },
  {
    "title": "微软687亿美元收购动视暴雪Activision Blizzard",
    "url": "https://bbs.byr.cn/article/OverWatch/1242",
    "count": 1
  },
  {
    "title": "北京下雪啦！！！",
    "url": "https://bbs.byr.cn/article/Picture/3311536",
    "count": 1
  },
  {
    "title": "突然什么也不想做",
    "url": "https://bbs.byr.cn/article/Feeling/3182294",
    "count": 1
  }
]