[
  {
    "title": "秋招ofer求比较：北京银行vs北京移动vs央企信托公司",
    "url": "https://bbs.byr.cn/article/Job/2155746",
    "count": 5
  },
  {
    "title": "成年人的苦",
    "url": "https://bbs.byr.cn/article/FamilyLife/145323",
    "count": 3
  },
  {
    "title": "【开帖记录】做闪送员的二三事",
    "url": "https://bbs.byr.cn/article/Picture/3311227",
    "count": 3
  },
  {
    "title": "对于借钱不还的，怎么有效的催款呢",
    "url": "https://bbs.byr.cn/article/Talking/6325697",
    "count": 2
  },
  {
    "title": "埃森哲面试官：“我不知道北邮，北邮是一本吗？”",
    "url": "https://bbs.byr.cn/article/WorkLife/1180792",
    "count": 2
  },
  {
    "title": "[代征][王道]云南小姐姐征友啦~",
    "url": "https://bbs.byr.cn/article/Friends/2015004",
    "count": 2
  },
  {
    "title": "开端开端开端",
    "url": "https://bbs.byr.cn/article/TV/183827",
    "count": 2
  },
  {
    "title": "突然什么也不想做",
    "url": "https://bbs.byr.cn/article/Feeling/3182294",
    "count": 1
  },
  {
    "title": "清深 保研",
    "url": "https://bbs.byr.cn/article/AimGraduate/1213194",
    "count": 1
  }
]