[
  {
    "title": "中国人民银行征信中心，清算中心，金融数据中心求比对",
    "url": "https://bbs.byr.cn/article/Talking/6329465",
    "count": 2
  },
  {
    "title": "95北师博士小姐姐征友啦！！！",
    "url": "https://bbs.byr.cn/article/Friends/2017183",
    "count": 1
  },
  {
    "title": "码农荷兰找工事宜",
    "url": "https://bbs.byr.cn/article/GoAbroad/383011",
    "count": 1
  },
  {
    "title": "【求助】农发行总行研发岗，请问有学长学姐们了解吗？",
    "url": "https://bbs.byr.cn/article/Job/2157548",
    "count": 1
  },
  {
    "title": "找到个好东西",
    "url": "https://bbs.byr.cn/article/Shanxi/211346",
    "count": 1
  }
]