[
  {
    "title": "赛博朋克 末日废土 骇客 仿生人 之类的影视作品或者小说推荐吗",
    "url": "https://bbs.byr.cn/article/Talking/6397773",
    "count": 26
  },
  {
    "title": "求建议 在北京 不加班的公司 安全岗",
    "url": "https://bbs.byr.cn/article/WorkLife/1202996",
    "count": 23
  },
  {
    "title": "【转】超神准！星座小王子独创的新型占卜、來一起試玩一下！",
    "url": "https://bbs.byr.cn/article/Constellations/326533",
    "count": 15
  },
  {
    "title": "求问联想小新pro14怎么样",
    "url": "https://bbs.byr.cn/article/Notebook/183532",
    "count": 11
  },
  {
    "title": "【沙雕图-NOT-BOT-2023-08-03-P2】",
    "url": "https://bbs.byr.cn/article/Picture/3347196",
    "count": 10
  },
  {
    "title": "【offer求比较】光大科技部 农行北京研发中心",
    "url": "https://bbs.byr.cn/article/Job/2194191",
    "count": 8
  },
  {
    "title": "[挽尊]看到本版长时间没有发言，尝试讲讲故事",
    "url": "https://bbs.byr.cn/article/Ghost/91236",
    "count": 5
  },
  {
    "title": "关于雅思成绩",
    "url": "https://bbs.byr.cn/article/GoAbroad/393698",
    "count": 5
  },
  {
    "title": "达摩院【通义千文】招Speech\u0026amp;NLP实习生【长期有效】",
    "url": "https://bbs.byr.cn/article/AimGraduate/1225922",
    "count": 4
  },
  {
    "title": "【代征】帮同事真诚征友",
    "url": "https://bbs.byr.cn/article/Friends/2028497",
    "count": 2
  }
]