[
  {
    "title": "三大运营商取消各项福利应该是板上钉钉的事了",
    "url": "https://bbs.byr.cn/article/Talking/6385322",
    "count": 43
  },
  {
    "title": "【转】超神准！星座小王子独创的新型占卜、來一起試玩一下！",
    "url": "https://bbs.byr.cn/article/Constellations/326533",
    "count": 15
  },
  {
    "title": "【offer求比较】美团vs快手 春招",
    "url": "https://bbs.byr.cn/article/Job/2189254",
    "count": 14
  },
  {
    "title": "【代征】90后小哥哥寻有缘小姐姐（大量王道）",
    "url": "https://bbs.byr.cn/article/Friends/2039112",
    "count": 13
  },
  {
    "title": "【问题】",
    "url": "https://bbs.byr.cn/article/AimGraduate/1224069",
    "count": 13
  },
  {
    "title": "麦当劳几号开业啊",
    "url": "https://bbs.byr.cn/article/Picture/3339524",
    "count": 11
  },
  {
    "title": "广东公务员",
    "url": "https://bbs.byr.cn/article/CivilServant/49973",
    "count": 10
  },
  {
    "title": "关于 malloc(): memory corruption 的问题",
    "url": "https://bbs.byr.cn/article/CPP/102613",
    "count": 9
  },
  {
    "title": "CSC互助",
    "url": "https://bbs.byr.cn/article/GoAbroad/392170",
    "count": 5
  },
  {
    "title": "九年感情终是不如一时的高兴",
    "url": "https://bbs.byr.cn/article/Feeling/3198939",
    "count": 2
  }
]