[
  {
    "title": "【讨论】关于情侣间的消费问题【长文】【更新】",
    "url": "https://bbs.byr.cn/article/Feeling/3202653",
    "count": 136
  },
  {
    "title": "领导暗示强制加班一小时，难受，人要憋爆了",
    "url": "https://bbs.byr.cn/article/WorkLife/1203249",
    "count": 25
  },
  {
    "title": "【转】超神准！星座小王子独创的新型占卜、來一起試玩一下！",
    "url": "https://bbs.byr.cn/article/Constellations/326533",
    "count": 14
  },
  {
    "title": "【坐标北京】90年女生诚征友",
    "url": "https://bbs.byr.cn/article/Friends/2043617",
    "count": 11
  },
  {
    "title": "【沙雕图-NOT-BOT-2023-08-06】",
    "url": "https://bbs.byr.cn/article/Picture/3347338",
    "count": 10
  },
  {
    "title": "24fall美phd现在还卡10043吗",
    "url": "https://bbs.byr.cn/article/GoAbroad/393717",
    "count": 8
  },
  {
    "title": "你怎么知道我去了上海",
    "url": "https://bbs.byr.cn/article/Photo/276179",
    "count": 7
  },
  {
    "title": "专科填报",
    "url": "https://bbs.byr.cn/article/Talking/6397889",
    "count": 7
  },
  {
    "title": "急诊外地医院报销",
    "url": "https://bbs.byr.cn/article/Health/231189",
    "count": 4
  },
  {
    "title": "喜德盛这个品牌的山地车好吗",
    "url": "https://bbs.byr.cn/article/Cycling/174282",
    "count": 3
  }
]