[
  {
    "title": "借楼咨询，情感贴",
    "url": "https://bbs.byr.cn/article/Friends/2047775",
    "count": 8
  },
  {
    "title": "【校招offer决赛圈】腾讯 vs 阿里云 vs 山东邮政 vs 人寿杭研",
    "url": "https://bbs.byr.cn/article/Job/2201414",
    "count": 6
  },
  {
    "title": "我有办法送给省部级官员一幅山水画，并且他一定会接收",
    "url": "https://bbs.byr.cn/article/Talking/6406585",
    "count": 5
  },
  {
    "title": "国院大一新生，越来越后悔来北邮，求开导...",
    "url": "https://bbs.byr.cn/article/GoAbroad/395033",
    "count": 4
  },
  {
    "title": "事业单位合同工跟国企一个性质吧？",
    "url": "https://bbs.byr.cn/article/WorkLife/1207105",
    "count": 3
  },
  {
    "title": "把你手机号后三位留下来，一样的就搞对象吧~~~",
    "url": "https://bbs.byr.cn/article/Constellations/462125",
    "count": 2
  },
  {
    "title": "【问题】octave不好吗？",
    "url": "https://bbs.byr.cn/article/Matlab/13550",
    "count": 1
  },
  {
    "title": "爱打COC部落战的北邮人快来！",
    "url": "https://bbs.byr.cn/article/OnlineGame/43768",
    "count": 1
  }
]