[
  {
    "title": "【offer选择】上海烟草还是深圳教师？",
    "url": "https://bbs.byr.cn/article/Job/2188334",
    "count": 30
  },
  {
    "title": "北邮搬迁不如并入北师大",
    "url": "https://bbs.byr.cn/article/Picture/3339145",
    "count": 17
  },
  {
    "title": "卷不动了",
    "url": "https://bbs.byr.cn/article/WorkLife/1198730",
    "count": 16
  },
  {
    "title": "【转】超神准！星座小王子独创的新型占卜、來一起試玩一下！",
    "url": "https://bbs.byr.cn/article/Constellations/326533",
    "count": 13
  },
  {
    "title": "我喜欢一个人",
    "url": "https://bbs.byr.cn/article/Talking/6384219",
    "count": 10
  },
  {
    "title": "学C++真的不如java吗",
    "url": "https://bbs.byr.cn/article/CPP/102550",
    "count": 10
  },
  {
    "title": "【考研招生】曹傧教授在【信通院】招收23年考研学生",
    "url": "https://bbs.byr.cn/article/AimGraduate/1223538",
    "count": 10
  },
  {
    "title": "电信省公司",
    "url": "https://bbs.byr.cn/article/Fujian/462643",
    "count": 7
  },
  {
    "title": "【问题】旧货市场",
    "url": "https://bbs.byr.cn/article/DIYLife/48084",
    "count": 6
  },
  {
    "title": "月与镜",
    "url": "https://bbs.byr.cn/article/Photo/275118",
    "count": 5
  }
]