[
  {
    "title": "【发泄】分手了，但不知道原因，死去的记忆开始攻击我",
    "url": "https://bbs.byr.cn/article/Feeling/3201460",
    "count": 5
  },
  {
    "title": "知晓天空之蔚蓝",
    "url": "https://bbs.byr.cn/article/Photo/275905",
    "count": 3
  },
  {
    "title": "请问前辈们，射频这个方向现在怎么样",
    "url": "https://bbs.byr.cn/article/Job/2193073",
    "count": 3
  },
  {
    "title": "求一个奶妈级校外访问BT的教程",
    "url": "https://bbs.byr.cn/article/Talking/6392111",
    "count": 2
  },
  {
    "title": "选校建议 UCL or NUS",
    "url": "https://bbs.byr.cn/article/GoAbroad/392985",
    "count": 1
  },
  {
    "title": "【出租】北邮南区家属院",
    "url": "https://bbs.byr.cn/article/Home/135222",
    "count": 1
  },
  {
    "title": "为什么北邮电子信息专硕学位证还沿用老的工程硕士学位证格式",
    "url": "https://bbs.byr.cn/article/Picture/3344135",
    "count": 1
  }
]