[
  {
    "title": "听说有人霸凌保洁阿姨?",
    "url": "https://bbs.byr.cn/article/Talking/6391211",
    "count": 59
  },
  {
    "title": "【更新】电子院同学突患白血病......（结束捐助，谢谢大家）",
    "url": "https://bbs.byr.cn/article/Feeling/3200762",
    "count": 26
  },
  {
    "title": "【转】超神准！星座小王子独创的新型占卜、來一起試玩一下！",
    "url": "https://bbs.byr.cn/article/Constellations/326533",
    "count": 20
  },
  {
    "title": "武汉国企推荐",
    "url": "https://bbs.byr.cn/article/WorkLife/1199584",
    "count": 14
  },
  {
    "title": "对标苏联笑话的美式笑话",
    "url": "https://bbs.byr.cn/article/Picture/3343260",
    "count": 13
  },
  {
    "title": "接毕业照约拍 跟拍",
    "url": "https://bbs.byr.cn/article/Photo/275579",
    "count": 9
  },
  {
    "title": "新建了个byr投资交流群，欢迎各位进来讨论吹水",
    "url": "https://bbs.byr.cn/article/Financial/80130",
    "count": 8
  },
  {
    "title": "智能罐子顶帖就送1w～ 寻找推广合伙人",
    "url": "https://bbs.byr.cn/article/Entrepreneurship/29094",
    "count": 7
  },
  {
    "title": "广州是不是工资比深圳低30%+加班更多？",
    "url": "https://bbs.byr.cn/article/Cantonese/197942",
    "count": 7
  },
  {
    "title": "有没有大佬知道微众银行深圳的情况？",
    "url": "https://bbs.byr.cn/article/Job/2192555",
    "count": 6
  }
]