[
  {
    "title": "开个贴给学校总结经验用",
    "url": "https://bbs.byr.cn/article/Talking/6393538",
    "count": 10
  },
  {
    "title": "广州海珠区租房，求合租求推荐",
    "url": "https://bbs.byr.cn/article/Cantonese/198041",
    "count": 2
  },
  {
    "title": "【求助】有偿取名，费用99（别嫌弃，麦当当+奶茶的小钱）",
    "url": "https://bbs.byr.cn/article/Feeling/3199602",
    "count": 2
  },
  {
    "title": "极致诱惑草莓熊",
    "url": "https://bbs.byr.cn/article/Picture/3344417",
    "count": 2
  },
  {
    "title": "这个是星座小王子独创的新型占卜、來一起試玩一下！",
    "url": "https://bbs.byr.cn/article/Constellations/465260",
    "count": 2
  },
  {
    "title": "【征友】【王道】94年甜妹闺蜜真诚征友",
    "url": "https://bbs.byr.cn/article/Friends/2041476",
    "count": 2
  },
  {
    "title": "I Pray",
    "url": "https://bbs.byr.cn/article/Photo/275990",
    "count": 1
  },
  {
    "title": "实习offer比较：百度 VS 中信建投",
    "url": "https://bbs.byr.cn/article/WorkLife/1201248",
    "count": 1
  },
  {
    "title": "关于华夏基金暑期转正",
    "url": "https://bbs.byr.cn/article/Job/2193284",
    "count": 1
  }
]