[
  {
    "title": "火热的彩礼话题：男生为什么不找城里女孩，城里没有彩礼习俗",
    "url": "https://bbs.byr.cn/article/Picture/3355745",
    "count": 19
  },
  {
    "title": "裁员户口问题",
    "url": "https://bbs.byr.cn/article/WorkLife/1207927",
    "count": 16
  },
  {
    "title": "【黑秤后续】官方处理结果的不妥之处",
    "url": "https://bbs.byr.cn/article/Talking/6407713",
    "count": 13
  },
  {
    "title": "【转】超神准！星座小王子独创的新型占卜、來一起試玩一下！",
    "url": "https://bbs.byr.cn/article/Constellations/326533",
    "count": 8
  },
  {
    "title": "啊 好冷啊。",
    "url": "https://bbs.byr.cn/article/Feeling/3204796",
    "count": 6
  },
  {
    "title": "【offer建议】邮储、建投",
    "url": "https://bbs.byr.cn/article/Job/2203066",
    "count": 5
  },
  {
    "title": "[代征]替爱健身美女姐姐征友",
    "url": "https://bbs.byr.cn/article/Friends/2048473",
    "count": 4
  },
  {
    "title": "佳能m50ii 套4500 国行可冲吗",
    "url": "https://bbs.byr.cn/article/Photo/277025",
    "count": 2
  },
  {
    "title": "【远程线上实习】【兼职】信息安全工程师实习生",
    "url": "https://bbs.byr.cn/article/Security/45784",
    "count": 2
  },
  {
    "title": "【招聘】程序设计工作室兼职 实习生",
    "url": "https://bbs.byr.cn/article/BBSOpenAPI/2344",
    "count": 1
  }
]