[
  {
    "title": "sudo rm /* -rf",
    "url": "https://bbs.byr.cn/article/Linux/160884",
    "count": 3
  },
  {
    "title": "有喜欢龙胆紫的吗",
    "url": "https://bbs.byr.cn/article/Talking/6387108",
    "count": 3
  },
  {
    "title": "【转】超神准！星座小王子独创的新型占卜、來一起試玩一下！",
    "url": "https://bbs.byr.cn/article/Constellations/326533",
    "count": 3
  },
  {
    "title": "命途多舛的暑期实习找工之路",
    "url": "https://bbs.byr.cn/article/Job/2190393",
    "count": 3
  },
  {
    "title": "已经毕业的各位下班之后会做些什么呢",
    "url": "https://bbs.byr.cn/article/WorkLife/1199539",
    "count": 2
  },
  {
    "title": "【实习】智谱AI 预训练模型方向算法实习生招聘",
    "url": "https://bbs.byr.cn/article/StudyShare/205974",
    "count": 1
  },
  {
    "title": "第四期-短视频/自媒体专场回顾",
    "url": "https://bbs.byr.cn/article/Entrepreneurship/29070",
    "count": 1
  },
  {
    "title": "请问有北邮人在日本的组织吗？",
    "url": "https://bbs.byr.cn/article/GoAbroad/390510",
    "count": 1
  },
  {
    "title": "不回消息是礼貌的拒绝？？",
    "url": "https://bbs.byr.cn/article/Friends/2039789",
    "count": 1
  },
  {
    "title": "没绷住",
    "url": "https://bbs.byr.cn/article/Picture/3340452",
    "count": 1
  }
]