[
  {
    "title": "妹妹高考志愿求助",
    "url": "https://bbs.byr.cn/article/StudyShare/207708",
    "count": 39
  },
  {
    "title": "看到小红书一位同学拍的北邮灯光秀",
    "url": "https://bbs.byr.cn/article/Picture/3365042",
    "count": 14
  },
  {
    "title": "【王道】96信通博士毕业生，给自己征友",
    "url": "https://bbs.byr.cn/article/Friends/2054430",
    "count": 9
  },
  {
    "title": "沙雕图 2024.6.27",
    "url": "https://bbs.byr.cn/article/Joke/731389",
    "count": 8
  },
  {
    "title": "感觉最近日本搞舆论搞得挺勤快的",
    "url": "https://bbs.byr.cn/article/Talking/6420686",
    "count": 5
  },
  {
    "title": "【问题】中证登北分社招",
    "url": "https://bbs.byr.cn/article/WorkLife/1216552",
    "count": 5
  },
  {
    "title": "【兼职】【实习】驻场1个月，安全产品python后台开发，2w/月",
    "url": "https://bbs.byr.cn/article/Security/45801",
    "count": 4
  },
  {
    "title": "你好，北邮；再见，北邮。",
    "url": "https://bbs.byr.cn/article/Feeling/3208308",
    "count": 4
  },
  {
    "title": "【7.24出发】新疆9日定制团摇人～",
    "url": "https://bbs.byr.cn/article/Travel/147872",
    "count": 4
  },
  {
    "title": "【转】超神准！星座小王子独创的新型占卜、來一起試玩一下！",
    "url": "https://bbs.byr.cn/article/Constellations/326533",
    "count": 2
  }
]