[
  {
    "title": "毕业20年后回到母校是什么感觉",
    "url": "https://bbs.byr.cn/article/Feeling/3205804",
    "count": 5
  },
  {
    "title": "【转】超神准！星座小王子独创的新型占卜、來一起試玩一下！",
    "url": "https://bbs.byr.cn/article/Constellations/326533",
    "count": 2
  },
  {
    "title": "求问电子缘胡宗海老师的纳米材料及应用",
    "url": "https://bbs.byr.cn/article/Picture/3358730",
    "count": 2
  },
  {
    "title": "大二咨询cs考研相关事宜",
    "url": "https://bbs.byr.cn/article/Talking/6411516",
    "count": 2
  },
  {
    "title": "【offer求比较】地点重庆，中移物联网 vs 长安",
    "url": "https://bbs.byr.cn/article/Job/2207849",
    "count": 1
  },
  {
    "title": "22届wxg背星，求校友们推荐工作",
    "url": "https://bbs.byr.cn/article/WorkLife/1194516",
    "count": 1
  },
  {
    "title": "蹲蹲有无3月中旬想去川西的姐妹",
    "url": "https://bbs.byr.cn/article/Travel/147225",
    "count": 1
  },
  {
    "title": "北邮2024管科813复试辅导学生",
    "url": "https://bbs.byr.cn/article/AimGraduate/1228250",
    "count": 1
  },
  {
    "title": "【2.27】坛服进度",
    "url": "https://bbs.byr.cn/article/Tshirt/91284",
    "count": 1
  },
  {
    "title": "求教去美国参加学术会议会被卡签证吗？",
    "url": "https://bbs.byr.cn/article/GoAbroad/396338",
    "count": 1
  }
]