[
  {
    "title": "【转】超神准！星座小王子独创的新型占卜、來一起試玩一下！",
    "url": "https://bbs.byr.cn/article/Constellations/326533",
    "count": 5
  },
  {
    "title": "在学校浴室丢失手机的32小时（二）",
    "url": "https://bbs.byr.cn/article/Talking/6413814",
    "count": 3
  },
  {
    "title": "吵架时男朋友沉默到底是在回避什么？",
    "url": "https://bbs.byr.cn/article/Feeling/3206437",
    "count": 2
  },
  {
    "title": "沙雕图2024.4.6",
    "url": "https://bbs.byr.cn/article/Picture/3360103",
    "count": 2
  },
  {
    "title": "【公告】“制作一颗科普卫星”挑战性课程开放选课",
    "url": "https://bbs.byr.cn/article/StudyShare/207349",
    "count": 1
  },
  {
    "title": "佳能玉渊潭求点播",
    "url": "https://bbs.byr.cn/article/Photo/277544",
    "count": 1
  },
  {
    "title": "【问题】25考研择校求助",
    "url": "https://bbs.byr.cn/article/AimGraduate/1229057",
    "count": 1
  }
]