[
  {
    "title": "【offer求比较】人寿研发中心 vs 北京事业单位",
    "url": "https://bbs.byr.cn/article/Job/2207413",
    "count": 12
  },
  {
    "title": "【出】宝马新能源车官方赠送【充电桩】",
    "url": "https://bbs.byr.cn/article/AutoMotor/129767",
    "count": 8
  },
  {
    "title": "【转】超神准！星座小王子独创的新型占卜、來一起試玩一下！",
    "url": "https://bbs.byr.cn/article/Constellations/326533",
    "count": 7
  },
  {
    "title": "最后给自己失败的博士申请画上一个句号",
    "url": "https://bbs.byr.cn/article/GoAbroad/395209",
    "count": 7
  },
  {
    "title": "沙雕图2024.2.22",
    "url": "https://bbs.byr.cn/article/Picture/3358452",
    "count": 6
  },
  {
    "title": "人工智能时代背景下，还需要锚死开发岗吗",
    "url": "https://bbs.byr.cn/article/Talking/6411006",
    "count": 6
  },
  {
    "title": "【王道】【杭州】帮98年小姐姐征友",
    "url": "https://bbs.byr.cn/article/Friends/2050571",
    "count": 5
  },
  {
    "title": "硕一年半，职业迷茫求指导",
    "url": "https://bbs.byr.cn/article/WorkLife/1210385",
    "count": 4
  },
  {
    "title": "正畸求问",
    "url": "https://bbs.byr.cn/article/Health/229923",
    "count": 2
  },
  {
    "title": "【问题】N1 87 各项得分 30 29 28 大概啥水平",
    "url": "https://bbs.byr.cn/article/Japanese/69319",
    "count": 1
  }
]