[
  {
    "title": "继神开之后盘点那些神分",
    "url": "https://bbs.byr.cn/article/Job/2210427",
    "count": 14
  },
  {
    "title": "关于电动车被偷又还回来",
    "url": "https://bbs.byr.cn/article/Talking/6415453",
    "count": 13
  },
  {
    "title": "回来学校论坛给自己征友~",
    "url": "https://bbs.byr.cn/article/Friends/2052390",
    "count": 13
  },
  {
    "title": "【求建议】32岁，继续编制里待着还是跳出去",
    "url": "https://bbs.byr.cn/article/WorkLife/1213557",
    "count": 9
  },
  {
    "title": "寻找五一内蒙古自驾游搭子",
    "url": "https://bbs.byr.cn/article/Travel/147460",
    "count": 8
  },
  {
    "title": "【转】超神准！星座小王子独创的新型占卜、來一起試玩一下！",
    "url": "https://bbs.byr.cn/article/Constellations/326533",
    "count": 6
  },
  {
    "title": "沙雕图2024.4.17",
    "url": "https://bbs.byr.cn/article/Picture/3360773",
    "count": 5
  },
  {
    "title": "在单位看到辆闪电",
    "url": "https://bbs.byr.cn/article/Cycling/174462",
    "count": 3
  },
  {
    "title": "本部食堂喜欢吃的窗口全换了。。",
    "url": "https://bbs.byr.cn/article/Food/525929",
    "count": 3
  },
  {
    "title": "电子科学与技术有啥报考岗位推荐吗",
    "url": "https://bbs.byr.cn/article/CivilServant/50663",
    "count": 2
  }
]