[
  {
    "title": "横渡琼州海峡，9年终圆梦——北邮游泳馆，梦开始的地方",
    "url": "https://bbs.byr.cn/article/Swim/130620",
    "count": 40
  },
  {
    "title": "沙雕图 2024.11.2",
    "url": "https://bbs.byr.cn/article/Joke/732892",
    "count": 6
  },
  {
    "title": "「北京征友」90年男生加油努力勇敢",
    "url": "https://bbs.byr.cn/article/Friends/2056517",
    "count": 6
  },
  {
    "title": "【转】超神准！星座小王子独创的新型占卜、來一起試玩一下！",
    "url": "https://bbs.byr.cn/article/Constellations/326533",
    "count": 4
  },
  {
    "title": "婚前买房还是婚后买房？",
    "url": "https://bbs.byr.cn/article/Talking/6429439",
    "count": 4
  },
  {
    "title": "【比较】【25秋招】【选择咨询】国企和互联网怎么权衡",
    "url": "https://bbs.byr.cn/article/Job/2218375",
    "count": 3
  },
  {
    "title": "江苏省电信中电鸿信",
    "url": "https://bbs.byr.cn/article/WorkLife/1221509",
    "count": 2
  },
  {
    "title": "实盘贴 北邮丁真",
    "url": "https://bbs.byr.cn/article/Picture/3368556",
    "count": 2
  },
  {
    "title": "北邮租房群",
    "url": "https://bbs.byr.cn/article/Home/138199",
    "count": 1
  },
  {
    "title": "江西电信面试",
    "url": "https://bbs.byr.cn/article/Jiangxi/469576",
    "count": 1
  }
]